BAv2/BAv2.py
BAv2/__init__.py
pyBAv-5.4.1.dist-info/METADATA
pyBAv-5.4.1.dist-info/WHEEL
pyBAv-5.4.1.dist-info/top_level.txt
pyBAv-5.4.1.dist-info/RECORD
