Metadata-Version: 2.1
Name: pyBAv
Version: 5.4.1
Summary: BAv2 is simple personalised  chatbot for every user and developer
Home-page: https://github.com/Srinadhch07/Personal-Projects-.git
Download-URL: https://github.com/Srinadhch07/Personal-Projects-.git
Author: Srinadhch07
Author-email: srinadhc07@gmail.com
License: MIT
Keywords: chatbot,info,personalai,search
Classifier: Development Status :: 5 - Production/Stable
Classifier: Intended Audience :: Developers
Classifier: Topic :: Software Development :: Build Tools
Classifier: License :: OSI Approved :: MIT License
Classifier: Programming Language :: Python :: 3.8
Classifier: Programming Language :: Python :: 3.9
Classifier: Programming Language :: Python :: 3.10
Requires-Dist: google-generativeai
